template_specialize/__init__.py
template_specialize/__main__.py
template_specialize/aws_parameter_store.py
template_specialize/main.py
template_specialize-1.6.0.dist-info/licenses/LICENSE
template_specialize-1.6.0.dist-info/METADATA
template_specialize-1.6.0.dist-info/WHEEL
template_specialize-1.6.0.dist-info/entry_points.txt
template_specialize-1.6.0.dist-info/top_level.txt
template_specialize-1.6.0.dist-info/RECORD
