Metadata-Version: 2.4
Name: template-specialize
Version: 1.6.0
Summary: Command-line tool for rendering Jinja2 templates
Home-page: https://github.com/craigahobbs/template-specialize
Author: Craig A. Hobbs
Author-email: craigahobbs@gmail.com
License: MIT
Keywords: jinja2,template,render,specialize
Classifier: Development Status :: 5 - Production/Stable
Classifier: Intended Audience :: Developers
Classifier: Operating System :: OS Independent
Classifier: Programming Language :: Python :: 3.9
Classifier: Programming Language :: Python :: 3.10
Classifier: Programming Language :: Python :: 3.11
Classifier: Programming Language :: Python :: 3.12
Classifier: Programming Language :: Python :: 3.13
Classifier: Programming Language :: Python :: 3.14
Classifier: Topic :: Utilities
License-File: LICENSE
Requires-Dist: jinja2>=2.10
Dynamic: license-file
